testmon/__init__.py
testmon/configure.py
testmon/db.py
testmon/process_code.py
testmon/pytest_testmon.py
testmon/testmon_core.py
testmon/tox_testmon.py
pytest_testmon_oc-1.0.0.dist-info/LICENSE
pytest_testmon_oc-1.0.0.dist-info/METADATA
pytest_testmon_oc-1.0.0.dist-info/WHEEL
pytest_testmon_oc-1.0.0.dist-info/entry_points.txt
pytest_testmon_oc-1.0.0.dist-info/top_level.txt
pytest_testmon_oc-1.0.0.dist-info/RECORD
